pyvscodeextroh/__init__.py
pyvscodeextroh/__main__.py
pyvscodeextroh/exceptions.py
pyvscodeextroh/manager.py
pyvscodeextroh/policy.py
pyvscodeextroh/policy_editor.py
pyvscodeextroh/utils.py
pyvscodeextroh-0.0.1.dist-info/licenses/LICENSE
pyvscodeextroh-0.0.1.dist-info/METADATA
pyvscodeextroh-0.0.1.dist-info/WHEEL
pyvscodeextroh-0.0.1.dist-info/top_level.txt
pyvscodeextroh-0.0.1.dist-info/RECORD
