Metadata-Version: 2.4
Name: pyvscodeextroh
Version: 0.0.1
Summary: A python package to manage vscode extensions.
Author: IT-Administrators
Maintainer: IT-Administrators
License: MIT License
Project-URL: Homepage, https://github.com/IT-Administrators/pyvscodeextroh
Keywords: extensions,extension,vscode,manage
Classifier: Programming Language :: Python :: 3
Classifier: License :: OSI Approved :: MIT License
Classifier: Operating System :: POSIX :: Linux
Requires-Python: >=3.7
License-File: LICENSE
Dynamic: license-file
